scrapy_smawe/__init__.py
scrapy_smawe/downloader_middleware.py
scrapy_smawe/settings.py
scrapy_smawe/spider_middleware.py
scrapy_smawe-0.1.dist-info/METADATA
scrapy_smawe-0.1.dist-info/WHEEL
scrapy_smawe-0.1.dist-info/top_level.txt
scrapy_smawe-0.1.dist-info/RECORD
