Metadata-Version: 2.1
Name: scrapy-smawe
Version: 0.1
Summary: smawe scrapy notes
Author: Samwe
Author-email: 1281722462@qq.com
License: MIT
Classifier: License :: OSI Approved :: MIT License
Classifier: Programming Language :: Python :: 3
Classifier: Programming Language :: Python :: Implementation :: CPython
Requires-Python: >=3.5.0
